yt_text_extractor/__init__.py
yt_text_extractor-0.1.0.dist-info/METADATA
yt_text_extractor-0.1.0.dist-info/WHEEL
yt_text_extractor-0.1.0.dist-info/entry_points.txt
yt_text_extractor-0.1.0.dist-info/top_level.txt
yt_text_extractor-0.1.0.dist-info/RECORD
