Metadata-Version: 2.1
Name: yt-text-extractor
Version: 0.1.0
Summary: Handy yt-dlp wrapper to download Youtube videos transcripts
Author-email: Alexander Ryabov <alex.ryabov@gmail.com>
Project-URL: Homepage, https://github.com/haron/yt-text-extractor
Project-URL: Issues, https://github.com/haron/yt-text-extractor/issues
Classifier: Programming Language :: Python :: 3
Classifier: Operating System :: OS Independent
Requires-Python: >=3.12
Requires-Dist: yt-dlp ==2024.10.07
Requires-Dist: ConfigArgParse >=1.7
Provides-Extra: test
Requires-Dist: pytest >=8.0.0 ; extra == 'test'
